llm_list/__init__.py
llm_list/__main__.py
llm_list/scrapers/__init__.py
llm_list/scrapers/base.py
llm_list/scrapers/huggingface.py
llm_list/scrapers/ollama.py
llm_list-0.1.0.dist-info/licenses/LICENSE
tests/__init__.py
tests/conftest.py
tests/test_base_scraper.py
tests/test_cli.py
tests/test_huggingface_scraper.py
tests/test_ollama_scraper.py
llm_list-0.1.0.dist-info/METADATA
llm_list-0.1.0.dist-info/WHEEL
llm_list-0.1.0.dist-info/entry_points.txt
llm_list-0.1.0.dist-info/top_level.txt
llm_list-0.1.0.dist-info/RECORD
