Metadata-Version: 2.4
Name: llm-list
Version: 0.1.0
Summary: A Python package to list and monitor available LLM models from various providers
Home-page: https://github.com/yourusername/llm-list
Author: Your Name
Author-email: Tom Sapletta <info@softreck.dev>
License: Apache-2.0
Project-URL: Homepage, https://github.com/softreck/llm-list
Project-URL: Documentation, https://github.com/softreck/llm-list#readme
Project-URL: Repository, https://github.com/softreck/llm-list
Project-URL: Changelog, https://github.com/softreck/llm-list/blob/main/CHANGELOG.md
Project-URL: Bug-Tracker, https://github.com/softreck/llm-list/issues
Classifier: Development Status :: 3 - Alpha
Classifier: Intended Audience :: Developers
Classifier: Intended Audience :: Science/Research
Classifier: License :: OSI Approved :: Apache Software License
Classifier: Operating System :: OS Independent
Classifier: Programming Language :: Python :: 3
Classifier: Programming Language :: Python :: 3.8
Classifier: Programming Language :: Python :: 3.9
Classifier: Programming Language :: Python :: 3.10
Classifier: Programming Language :: Python :: 3.11
Classifier: Topic :: Scientific/Engineering
Classifier: Topic :: Scientific/Engineering :: Artificial Intelligence
Classifier: Topic :: Software Development
Classifier: Topic :: Software Development :: Libraries
Classifier: Topic :: Software Development :: Libraries :: Python Modules
Requires-Python: >=3.8
License-File: LICENSE
Requires-Dist: requests>=2.25.0
Requires-Dist: beautifulsoup4>=4.9.0
Requires-Dist: python-dotenv>=0.19.0
Requires-Dist: tqdm>=4.61.0
Requires-Dist: pydantic>=1.8.0
Provides-Extra: dev
Requires-Dist: pytest>=6.0.0; extra == "dev"
Requires-Dist: pytest-cov>=2.8.0; extra == "dev"
Requires-Dist: black>=21.5b2; extra == "dev"
Requires-Dist: isort>=5.0.0; extra == "dev"
Requires-Dist: mypy>=0.800; extra == "dev"
Requires-Dist: flake8>=3.9.0; extra == "dev"
Requires-Dist: pre-commit>=2.12.0; extra == "dev"
Requires-Dist: twine>=3.4.0; extra == "dev"
Requires-Dist: build>=0.3.0; extra == "dev"
Requires-Dist: types-requests>=2.25.0; extra == "dev"
Dynamic: author
Dynamic: home-page
Dynamic: license-file
Dynamic: requires-python
